{
  "date": "2026-06-25",
  "generated_at": "2026-06-25T05:06:18.440308+00:00",
  "cycle_phase": "BEAR",
  "transition_zone": false,
  "composite_action_code": "NO_ACTION",
  "composite_short_label": "No Action",
  "signal_state": "NO_ACTION",
  "hold_horizon": "N/A",
  "composite_description": "No drawdown signal. Conditions do not meet any entry threshold.",
  "backtest_note": "",
  "corroboration": "NONE",
  "matrix_key": "BEAR x NO_ACTION",
  "structural_risk": false,
  "structural_reasons": [],
  "btc_drawdown_tier": "NONE",
  "btc_zscore": 0.047,
  "btc_pct_below_1yr_high": -49.79,
  "btc_rv30": 35.7,
  "eth_drawdown_tier": "NONE",
  "sol_drawdown_tier": "NONE",
  "fear_greed": 12,
  "days_in_state": 6,
  "tier": "A",
  "brief": "BTC remains 14.8pp below the -35% drawdown threshold (worsening trajectory) and 4.3pp above the 40% volatility floor (improving). A crisis z-score below -3.0 would trigger CRISIS_ENTRY; alternatively, price recovering above the 200d MA would flip the regime and enable tactical opportunities.",
  "outliers": []
}