{
  "date": "2026-05-14",
  "generated_at": "2026-05-14T00:00:00Z (historical)",
  "btc": {
    "price": 79277.8045,
    "return_5d_pct": -1.14,
    "return_30d_pct": 6.39,
    "return_5d_zscore": -0.19,
    "pct_from_ath_1yr": -36.46,
    "above_ma200": false,
    "above_ma50": true,
    "ma_cross": "death",
    "funding_rate_daily": null,
    "funding_annualised": null,
    "funding_avg_5d": null,
    "funding_avg_10d": null,
    "funding_zscore": null,
    "funding_accel_ratio": null,
    "decel_grade": null,
    "fear_greed": 34,
    "dislocation_score": 41.0,
    "quadrant": "BUSINESS_AS_USUAL"
  },
  "eth": {
    "price": 2257.6171,
    "return_5d_pct": -2.13,
    "return_30d_pct": -4.82,
    "return_5d_zscore": -0.3,
    "pct_from_ath_1yr": -53.25,
    "above_ma200": false,
    "ma_cross": "death",
    "funding_rate_daily": null,
    "funding_annualised": null,
    "funding_zscore": null,
    "funding_accel_ratio": null,
    "decel_grade": null,
    "eth_btc_zscore": -0.83,
    "eth_relative_30d": -11.21,
    "dislocation_score": 31.3,
    "quadrant": "BUSINESS_AS_USUAL"
  },
  "sol": {
    "price": 91.0676,
    "return_5d_pct": -0.92,
    "return_30d_pct": 5.15,
    "return_5d_zscore": -0.07,
    "pct_from_ath_1yr": -63.21,
    "above_ma200": false,
    "ma_cross": "death",
    "funding_rate_daily": null,
    "funding_annualised": null,
    "funding_zscore": null,
    "funding_accel_ratio": null,
    "decel_grade": null,
    "sol_btc_zscore": -1.34,
    "sol_relative_30d": -1.24,
    "dislocation_score": 32.0,
    "quadrant": "BUSINESS_AS_USUAL"
  },
  "market_structure": {
    "btc_dominance_pct": 56.19,
    "eth_dominance_pct": 9.64,
    "btc_dominance_trend": "neutral",
    "total_market_cap_bn": 2478.2,
    "stablecoin_market_cap_bn": 263.8,
    "stablecoin_dominance_pct": 10.64,
    "eth_btc_ratio": 0.028477,
    "eth_btc_zscore": -0.83,
    "sol_btc_ratio": 0.001149,
    "sol_btc_zscore": -1.34
  },
  "cycle": {
    "phase": "BEAR",
    "description": "BTC below 200d MA -- macro downtrend",
    "confidence": "high",
    "above_ma200": false,
    "eth_rotating": false,
    "altcoin_season": false,
    "funding_positive": false
  },
  "composite_signal": {
    "action_code": "NO_ACTION",
    "short_label": "No Action",
    "description": "BEAR cycle with normal conditions -- nothing to do",
    "corroboration": "NONE",
    "matrix_key": "BEAR x BUSINESS_AS_USUAL"
  },
  "signals": {
    "btc_decel_grade": null,
    "eth_decel_grade": null,
    "sol_decel_grade": null,
    "eth_dislocated_vs_btc": false,
    "sol_dislocated_vs_btc": false,
    "altcoin_rotation_active": false,
    "eth_rotation_active": false,
    "fear_extreme": false,
    "greed_extreme": false
  }
}